zango/__init__.py
zango/api/__init__.py
zango/api/app_auth/__init__.py
zango/api/app_auth/urls.py
zango/api/app_auth/config/__init__.py
zango/api/app_auth/config/v1/__init__.py
zango/api/app_auth/config/v1/urls.py
zango/api/app_auth/config/v1/views.py
zango/api/app_auth/flows/__init__.py
zango/api/app_auth/flows/v1/__init__.py
zango/api/app_auth/flows/v1/forms.py
zango/api/app_auth/flows/v1/login.py
zango/api/app_auth/flows/v1/login_with_code.py
zango/api/app_auth/flows/v1/logout.py
zango/api/app_auth/flows/v1/mfa.py
zango/api/app_auth/flows/v1/password.py
zango/api/app_auth/flows/v1/role.py
zango/api/app_auth/flows/v1/saml.py
zango/api/app_auth/flows/v1/session.py
zango/api/app_auth/flows/v1/urls.py
zango/api/app_auth/profile/__init__.py
zango/api/app_auth/profile/v1/__init__.py
zango/api/app_auth/profile/v1/serializers.py
zango/api/app_auth/profile/v1/urls.py
zango/api/app_auth/profile/v1/utils.py
zango/api/app_auth/profile/v1/views.py
zango/api/platform/__init__.py
zango/api/platform/urls.py
zango/api/platform/accesslogs/__init__.py
zango/api/platform/accesslogs/v1/__init__.py
zango/api/platform/accesslogs/v1/serializers.py
zango/api/platform/accesslogs/v1/urls.py
zango/api/platform/accesslogs/v1/views.py
zango/api/platform/auditlogs/__init__.py
zango/api/platform/auditlogs/v1/__init__.py
zango/api/platform/auditlogs/v1/serializers.py
zango/api/platform/auditlogs/v1/urls.py
zango/api/platform/auditlogs/v1/views.py
zango/api/platform/auth/__init__.py
zango/api/platform/auth/v1/__init__.py
zango/api/platform/auth/v1/serializers.py
zango/api/platform/auth/v1/urls.py
zango/api/platform/auth/v1/views.py
zango/api/platform/codebase/__init__.py
zango/api/platform/codebase/v1/__init__.py
zango/api/platform/codebase/v1/serializers.py
zango/api/platform/codebase/v1/urls.py
zango/api/platform/codebase/v1/views.py
zango/api/platform/health/__init__.py
zango/api/platform/health/v1/__init__.py
zango/api/platform/health/v1/urls.py
zango/api/platform/health/v1/views.py
zango-1.0.4.dist-info/licenses/LICENSE
zango-1.0.4.dist-info/METADATA
zango-1.0.4.dist-info/WHEEL
zango-1.0.4.dist-info/entry_points.txt
zango-1.0.4.dist-info/top_level.txt
zango-1.0.4.dist-info/RECORD
