Metadata-Version: 2.4
Name: zango
Version: 1.0.4
Summary: Zango: multi-tenant Django framework for building business apps
Home-page: https://github.com/Healthlane-Technologies/Zango
Author: Zelthy ("Healthlane Technologies")
Author-email: maintainers@zelthy.com
License: Apache License 2.0
Project-URL: Bug Reports, https://github.com/Healthlane-Technologies/Zango/issues
Project-URL: Source, https://github.com/Healthlane-Technologies/Zango
Project-URL: Documentation, https://github.com/Healthlane-Technologies/Zango#readme
Keywords: django multi-tenant framework business apps
Classifier: Development Status :: 5 - Production/Stable
Classifier: Framework :: Django
Classifier: Intended Audience :: Developers
Classifier: License :: OSI Approved :: Apache Software License
Classifier: Operating System :: OS Independent
Classifier: Programming Language :: Python
Classifier: Programming Language :: Python :: 3
Classifier: Programming Language :: Python :: 3.8
Classifier: Programming Language :: Python :: 3.9
Classifier: Programming Language :: Python :: 3.10
Classifier: Programming Language :: Python :: 3.11
Classifier: Programming Language :: Python :: 3.12
Classifier: Topic :: Internet :: WWW/HTTP
Classifier: Topic :: Internet :: WWW/HTTP :: Dynamic Content
Classifier: Topic :: Software Development :: Libraries :: Python Modules
Requires-Python: >=3.8
License-File: LICENSE
Requires-Dist: beautifulsoup4==4.12.3
Requires-Dist: boto3==1.28.52
Requires-Dist: botocore==1.31.85
Requires-Dist: celery==5.3.1
Requires-Dist: click==8.1.7
Requires-Dist: cookiecutter==2.3.0
Requires-Dist: coverage==7.6.1
Requires-Dist: crispy-bootstrap5==0.7
Requires-Dist: cryptography==44.0.3
Requires-Dist: django==4.2.16
Requires-Dist: django-axes==6.4.0
Requires-Dist: django-cachalot==2.6.1
Requires-Dist: django-celery-beat==2.5.0
Requires-Dist: django-celery-results==2.5.1
Requires-Dist: django-cors-headers==4.2.0
Requires-Dist: django-crispy-forms==2.0
Requires-Dist: django-debug-toolbar==4.2.0
Requires-Dist: django-decorator-include==3.0
Requires-Dist: django-environ==0.11.2
Requires-Dist: django-formtools==2.4.1
Requires-Dist: django-ipware==7.0.1
Requires-Dist: django-phonenumber-field==7.1.0
Requires-Dist: django-recaptcha==4.1.0
Requires-Dist: django-redis==5.3.0
Requires-Dist: django-rest-knox==5.0.2
Requires-Dist: django-session-security==2.6.7
Requires-Dist: django-smtp-ssl==1.0
Requires-Dist: django-storages==1.14
Requires-Dist: django-tenants==3.6.1
Requires-Dist: djangorestframework==3.15.2
Requires-Dist: docusign-esign==5.2.0
Requires-Dist: fido2==2.0.0
Requires-Dist: flake8==6.1.0
Requires-Dist: flower==2.0.1
Requires-Dist: GitPython==3.1.43
Requires-Dist: gunicorn==23.0.0
Requires-Dist: jsonschema==4.24.0
Requires-Dist: line-bot-sdk==3.17.1
Requires-Dist: loguru==0.7.2
Requires-Dist: lxml==5.3.0
Requires-Dist: openai==1.97.1
Requires-Dist: openpyxl==3.1.5
Requires-Dist: openpyxl==3.1.5
Requires-Dist: opentelemetry-api==1.22.0
Requires-Dist: opentelemetry-distro==0.43b0
Requires-Dist: opentelemetry-exporter-otlp==1.22.0
Requires-Dist: opentelemetry-exporter-otlp-proto-common==1.22.0
Requires-Dist: opentelemetry-exporter-otlp-proto-grpc==1.22.0
Requires-Dist: opentelemetry-exporter-otlp-proto-http==1.22.0
Requires-Dist: opentelemetry-instrumentation==0.43b0
Requires-Dist: opentelemetry-instrumentation-asgi==0.43b0
Requires-Dist: opentelemetry-instrumentation-aws-lambda==0.43b0
Requires-Dist: opentelemetry-instrumentation-boto3sqs==0.43b0
Requires-Dist: opentelemetry-instrumentation-botocore==0.43b0
Requires-Dist: opentelemetry-instrumentation-celery==0.43b0
Requires-Dist: opentelemetry-instrumentation-dbapi==0.43b0
Requires-Dist: opentelemetry-instrumentation-django==0.43b0
Requires-Dist: opentelemetry-instrumentation-grpc==0.43b0
Requires-Dist: opentelemetry-instrumentation-jinja2==0.43b0
Requires-Dist: opentelemetry-instrumentation-logging==0.43b0
Requires-Dist: opentelemetry-instrumentation-psycopg2==0.43b0
Requires-Dist: opentelemetry-instrumentation-redis==0.43b0
Requires-Dist: opentelemetry-instrumentation-requests==0.43b0
Requires-Dist: opentelemetry-instrumentation-sqlite3==0.43b0
Requires-Dist: opentelemetry-instrumentation-urllib==0.43b0
Requires-Dist: opentelemetry-instrumentation-urllib3==0.43b0
Requires-Dist: opentelemetry-instrumentation-wsgi==0.43b0
Requires-Dist: opentelemetry-propagator-aws-xray==1.0.1
Requires-Dist: opentelemetry-proto==1.22.0
Requires-Dist: opentelemetry-sdk==1.22.0
Requires-Dist: opentelemetry-semantic-conventions==0.43b0
Requires-Dist: opentelemetry-util-http==0.43b0
Requires-Dist: packaging==24.1
Requires-Dist: pandas==2.3.0
Requires-Dist: pdfkit==1.0.0
Requires-Dist: phonenumberslite==8.13.23
Requires-Dist: pluginbase==1.0.1
Requires-Dist: pre-commit==3.8.0
Requires-Dist: psycopg2-binary==2.9.9
Requires-Dist: pycryptodome==3.23.0
Requires-Dist: pydub==0.25.1
Requires-Dist: PyJWT==2.8.0
Requires-Dist: PyMuPDF==1.26.3
Requires-Dist: PyPDF2==3.0.1
Requires-Dist: python3-saml==1.16.0
Requires-Dist: pytz==2024.1
Requires-Dist: setuptools==70.1.1
Requires-Dist: single-beat==0.6.3
Requires-Dist: sqlalchemy==2.0.41
Requires-Dist: XlsxWriter==3.1.9
Requires-Dist: xmlsec==1.3.14
Requires-Dist: zango-allauth==65.10.0
Dynamic: author
Dynamic: author-email
Dynamic: classifier
Dynamic: description
Dynamic: description-content-type
Dynamic: home-page
Dynamic: keywords
Dynamic: license
Dynamic: license-file
Dynamic: project-url
Dynamic: requires-dist
Dynamic: requires-python
Dynamic: summary
